bubble_aopy/__init__.py
bubble_aopy/bubble_ao_ponto.py
bubble_aopy-0.1.0.dist-info/METADATA
bubble_aopy-0.1.0.dist-info/WHEEL
bubble_aopy-0.1.0.dist-info/RECORD
