Metadata-Version: 2.1
Name: bubble-aopy
Version: 0.1.0
Summary: 
Author: Estevao
Author-email: estevaopfon@gmail.com
Requires-Python: >=3.11,<4.0
Classifier: Programming Language :: Python :: 3
Classifier: Programming Language :: Python :: 3.11
